django_workflow_engine/__init__.py
django_workflow_engine/apps.py
django_workflow_engine/dataclass.py
django_workflow_engine/exceptions.py
django_workflow_engine/executor.py
django_workflow_engine/generate_urls.py
django_workflow_engine/management/__init__.py
django_workflow_engine/management/commands/__init__.py
django_workflow_engine/management/commands/cleanup_workflow_engine.py
django_workflow_engine/migrations/0001_initial.py
django_workflow_engine/migrations/0002_alter_flow_workflow_name.py
django_workflow_engine/migrations/0003_taskrecord_broke_flow.py
django_workflow_engine/migrations/0004_auto_20211116_0823.py
django_workflow_engine/migrations/0005_rename_finished_at_taskrecord_executed_at.py
django_workflow_engine/migrations/0006_taskrecord_done.py
django_workflow_engine/migrations/0007_flow_running.py
django_workflow_engine/migrations/0008_remove_taskrecord_broke_flow.py
django_workflow_engine/migrations/0009_rename_taskrecord_taskrecordexecution_and_create_new_taskstatus.py
django_workflow_engine/migrations/0010_create_replacement_task_record.py
django_workflow_engine/migrations/0011_migrate_from_taskrecordexecutions.py
django_workflow_engine/migrations/0012_alter_target_unique_together.py
django_workflow_engine/migrations/__init__.py
django_workflow_engine/models.py
django_workflow_engine/tasks/__init__.py
django_workflow_engine/tasks/email_form.py
django_workflow_engine/tasks/previous_tasks_complete.py
django_workflow_engine/tasks/send_email.py
django_workflow_engine/tasks/task.py
django_workflow_engine/templates/django_workflow_engine/flow-continue.html
django_workflow_engine/templates/django_workflow_engine/flow_detail.html
django_workflow_engine/templates/django_workflow_engine/flow_diagram.html
django_workflow_engine/templates/django_workflow_engine/flow_form.html
django_workflow_engine/templates/django_workflow_engine/flow_list.html
django_workflow_engine/templates/includes/requirement_summary.html
django_workflow_engine/tests/__init__.py
django_workflow_engine-0.2.2.dist-info/LICENSE
django_workflow_engine-0.2.2.dist-info/METADATA
django_workflow_engine-0.2.2.dist-info/WHEEL
django_workflow_engine-0.2.2.dist-info/RECORD
