Metadata-Version: 2.1
Name: django-workflow-engine
Version: 0.2.2
Summary: 
License: MIT
Author: Cameron Lamb
Author-email: cameron.lamb@digital.trade.gov.uk
Requires-Python: >=3.9,<4.0
Classifier: License :: OSI Approved :: MIT License
Classifier: Programming Language :: Python :: 3
Classifier: Programming Language :: Python :: 3.9
Classifier: Programming Language :: Python :: 3.10
Classifier: Programming Language :: Python :: 3.11
Classifier: Programming Language :: Python :: 3.12
